sqlmodel_mypy/__init__.py
sqlmodel_mypy/persisted.py
sqlmodel_mypy/plugin.py
sqlmodel_mypy/py.typed
sqlmodel_mypy/transform.py
sqlmodel_mypy_plugin-0.19.1.dist-info/METADATA
sqlmodel_mypy_plugin-0.19.1.dist-info/WHEEL
sqlmodel_mypy_plugin-0.19.1.dist-info/licenses/LICENSE
sqlmodel_mypy_plugin-0.19.1.dist-info/RECORD
