Metadata-Version: 2.4
Name: sqlmodel-mypy-plugin
Version: 0.19.1
Summary: Mypy plugin for SQLModel (better constructor/Field typing).
Project-URL: Homepage, https://github.com/sertione/sqlmodel-mypy-plugin
Project-URL: Repository, https://github.com/sertione/sqlmodel-mypy-plugin
Project-URL: Issues, https://github.com/sertione/sqlmodel-mypy-plugin/issues
Project-URL: Changelog, https://github.com/sertione/sqlmodel-mypy-plugin/releases
Author: sertione
License: MIT License
License-File: LICENSE
Keywords: mypy,plugin,pydantic,sqlalchemy,sqlmodel,typing
Classifier: Development Status :: 4 - Beta
Classifier: Intended Audience :: Developers
Classifier: License :: OSI Approved :: MIT License
Classifier: Programming Language :: Python :: 3 :: Only
Classifier: Programming Language :: Python :: 3.10
Classifier: Programming Language :: Python :: 3.11
Classifier: Programming Language :: Python :: 3.12
Classifier: Programming Language :: Python :: 3.13
Classifier: Typing :: Typed
Requires-Python: >=3.10
Requires-Dist: mypy>=1.19.1
Requires-Dist: typing-extensions>=4.10.0
